{"_approachDistance": 50, "_approachTime": 1, "_name": "", "_notes": [{"_time": 0.303, "_x": 1, "_y": 1}, {"_time": 0.52, "_x": -1, "_y": 0}, {"_time": 0.607, "_x": -1, "_y": -1}, {"_time": 0.827, "_x": 1, "_y": -1}, {"_time": 0.957, "_x": 0, "_y": 1}, {"_time": 1.132, "_x": 0, "_y": -1}, {"_time": 1.305, "_x": -1, "_y": 1}, {"_time": 1.481, "_x": 1, "_y": -1}, {"_time": 1.654, "_x": -1, "_y": 0}, {"_time": 1.916, "_x": 1, "_y": 1}, {"_time": 2.003, "_x": 1, "_y": 0}, {"_time": 2.223, "_x": -1, "_y": 0}, {"_time": 2.353, "_x": 0, "_y": 1}, {"_time": 2.528, "_x": 0, "_y": -1}, {"_time": 2.701, "_x": 1, "_y": 1}, {"_time": 2.877, "_x": -1, "_y": -1}, {"_time": 3.05, "_x": 1, "_y": 0}, {"_time": 3.312, "_x": -1, "_y": 0}, {"_time": 3.399, "_x": -1, "_y": -1}, {"_time": 3.619, "_x": 1, "_y": 0}, {"_time": 3.749, "_x": 0, "_y": 1}, {"_time": 3.924, "_x": 0, "_y": -1}, {"_time": 4.097, "_x": -1, "_y": 1}, {"_time": 4.273, "_x": 1, "_y": -1}, {"_time": 4.446, "_x": -1, "_y": 0}, {"_time": 4.707, "_x": 1, "_y": 1}, {"_time": 4.794, "_x": 1, "_y": 0}, {"_time": 5.014, "_x": -1, "_y": 0}, {"_time": 5.144, "_x": 0, "_y": 1}, {"_time": 5.319, "_x": 0, "_y": -1}, {"_time": 5.492, "_x": 1, "_y": 1}, {"_time": 5.668, "_x": -1, "_y": -1}, {"_time": 5.841, "_x": 1, "_y": 0}, {"_time": 6.103, "_x": -1, "_y": 0}, {"_time": 6.19, "_x": -1, "_y": -1}, {"_time": 6.41, "_x": 1, "_y": 0}, {"_time": 6.54, "_x": 0, "_y": 1}, {"_time": 6.715, "_x": 0, "_y": -1}, {"_time": 6.888, "_x": -1, "_y": 1}, {"_time": 7.064, "_x": 1, "_y": -1}, {"_time": 7.237, "_x": -1, "_y": 0}, {"_time": 7.497, "_x": 1, "_y": 1}, {"_time": 7.584, "_x": 1, "_y": 0}, {"_time": 7.804, "_x": -1, "_y": 0}, {"_time": 7.934, "_x": 0, "_y": 1}, {"_time": 8.109, "_x": 0, "_y": -1}, {"_time": 8.282, "_x": 1, "_y": 1}, {"_time": 8.458, "_x": -1, "_y": -1}, {"_time": 8.631, "_x": 1, "_y": 0}, {"_time": 8.893, "_x": -1, "_y": 0}, {"_time": 8.98, "_x": -1, "_y": -1}, {"_time": 9.2, "_x": 1, "_y": 0}, {"_time": 9.33, "_x": 0, "_y": 1}, {"_time": 9.505, "_x": 0, "_y": -1}, {"_time": 9.678, "_x": -1, "_y": 1}, {"_time": 9.854, "_x": 1, "_y": -1}, {"_time": 10.202, "_x": 0, "_y": 0}, {"_time": 11.466, "_x": -1, "_y": 1}, {"_time": 11.641, "_x": 0, "_y": -1}, {"_time": 11.815, "_x": 0, "_y": 1}, {"_time": 11.9, "_x": -1, "_y": 0}, {"_time": 12.077, "_x": 1, "_y": 1}, {"_time": 12.251, "_x": 0, "_y": -1}, {"_time": 12.426, "_x": 0, "_y": 1}, {"_time": 12.511, "_x": 1, "_y": 0}, {"_time": 12.687, "_x": -1, "_y": 1}, {"_time": 12.862, "_x": -1, "_y": -1}, {"_time": 13.036, "_x": 1, "_y": 1}, {"_time": 13.211, "_x": -1, "_y": 0}, {"_time": 13.298, "_x": 0, "_y": -1}, {"_time": 13.471, "_x": 0, "_y": 0}, {"_time": 13.647, "_x": 1, "_y": -1}, {"_time": 13.821, "_x": -1, "_y": 1}, {"_time": 13.908, "_x": 0, "_y": 0}, {"_time": 14.083, "_x": -1, "_y": -1}, {"_time": 14.257, "_x": -1, "_y": -1}, {"_time": 14.432, "_x": 0, "_y": 1}, {"_time": 14.606, "_x": 0, "_y": -1}, {"_time": 14.691, "_x": -1, "_y": 0}, {"_time": 14.868, "_x": 1, "_y": -1}, {"_time": 15.042, "_x": 0, "_y": 1}, {"_time": 15.217, "_x": 0, "_y": -1}, {"_time": 15.302, "_x": 1, "_y": 0}, {"_time": 15.478, "_x": -1, "_y": -1}, {"_time": 15.653, "_x": -1, "_y": 1}, {"_time": 15.827, "_x": 1, "_y": -1}, {"_time": 16.002, "_x": -1, "_y": 0}, {"_time": 16.089, "_x": 0, "_y": 1}, {"_time": 16.262, "_x": 0, "_y": 0}, {"_time": 16.438, "_x": 1, "_y": 1}, {"_time": 16.612, "_x": -1, "_y": -1}, {"_time": 16.699, "_x": 0, "_y": 0}, {"_time": 16.874, "_x": -1, "_y": 1}, {"_time": 17.048, "_x": -1, "_y": 1}, {"_time": 17.223, "_x": 0, "_y": -1}, {"_time": 17.397, "_x": 0, "_y": 1}, {"_time": 17.482, "_x": -1, "_y": 0}, {"_time": 17.659, "_x": 1, "_y": 1}, {"_time": 17.833, "_x": 0, "_y": -1}, {"_time": 18.008, "_x": 0, "_y": 1}, {"_time": 18.093, "_x": 1, "_y": 0}, {"_time": 18.269, "_x": -1, "_y": 1}, {"_time": 18.444, "_x": -1, "_y": -1}, {"_time": 18.618, "_x": 1, "_y": 1}, {"_time": 18.793, "_x": -1, "_y": 0}, {"_time": 18.88, "_x": 0, "_y": -1}, {"_time": 19.053, "_x": 0, "_y": 0}, {"_time": 19.229, "_x": 1, "_y": -1}, {"_time": 19.403, "_x": -1, "_y": 1}, {"_time": 19.49, "_x": 0, "_y": 0}, {"_time": 19.665, "_x": -1, "_y": -1}, {"_time": 19.839, "_x": -1, "_y": -1}, {"_time": 20.014, "_x": 0, "_y": 1}, {"_time": 20.188, "_x": 0, "_y": -1}, {"_time": 20.273, "_x": -1, "_y": 0}, {"_time": 20.491, "_x": 1, "_y": 0}, {"_time": 20.532, "_x": 1, "_y": -1}, {"_time": 20.84, "_x": -1, "_y": 0}, {"_time": 20.881, "_x": 0, "_y": 1}, {"_time": 21.188, "_x": 1, "_y": -1}, {"_time": 21.231, "_x": 0, "_y": -1}, {"_time": 21.536, "_x": -1, "_y": 1}, {"_time": 21.579, "_x": 0, "_y": 1}, {"_time": 21.884, "_x": 0, "_y": -1}, {"_time": 21.927, "_x": -1, "_y": 0}, {"_time": 22.628, "_x": 0, "_y": 1}, {"_time": 22.845, "_x": 1, "_y": -1}, {"_time": 22.933, "_x": 0, "_y": 0}, {"_time": 23.326, "_x": -1, "_y": -1}, {"_time": 23.499, "_x": -1, "_y": 0}, {"_time": 23.63, "_x": -1, "_y": 1}, {"_time": 24.069, "_x": 1, "_y": 1}, {"_time": 24.156, "_x": 1, "_y": -1}, {"_time": 24.244, "_x": -1, "_y": -1}, {"_time": 24.331, "_x": -1, "_y": 1}, {"_time": 24.418, "_x": 1, "_y": 1}, {"_time": 24.505, "_x": 1, "_y": -1}, {"_time": 24.593, "_x": -1, "_y": -1}, {"_time": 24.68, "_x": -1, "_y": 1}, {"_time": 24.767, "_x": 1, "_y": 1}, {"_time": 24.854, "_x": 1, "_y": -1}, {"_time": 24.942, "_x": -1, "_y": -1}, {"_time": 25.029, "_x": -1, "_y": 1}, {"_time": 25.115, "_x": 1, "_y": 1}, {"_time": 25.203, "_x": 1, "_y": 1}, {"_time": 25.29, "_x": 1, "_y": 1}, {"_time": 25.42, "_x": -1, "_y": 0}, {"_time": 25.548, "_x": 1, "_y": -1}, {"_time": 25.68, "_x": 0, "_y": 0}, {"_time": 26.074, "_x": -1, "_y": 1}, {"_time": 26.247, "_x": -1, "_y": 0}, {"_time": 26.378, "_x": -1, "_y": -1}, {"_time": 26.86, "_x": -1, "_y": 1}, {"_time": 26.947, "_x": -1, "_y": -1}, {"_time": 27.035, "_x": 1, "_y": -1}, {"_time": 27.122, "_x": 1, "_y": 1}, {"_time": 27.209, "_x": -1, "_y": 1}, {"_time": 27.296, "_x": -1, "_y": -1}, {"_time": 27.384, "_x": 1, "_y": -1}, {"_time": 27.471, "_x": 1, "_y": 1}, {"_time": 27.558, "_x": -1, "_y": 1}, {"_time": 27.645, "_x": -1, "_y": -1}, {"_time": 27.733, "_x": 1, "_y": -1}, {"_time": 27.82, "_x": 1, "_y": 1}, {"_time": 27.906, "_x": -1, "_y": 1}, {"_time": 27.994, "_x": -1, "_y": 1}, {"_time": 28.081, "_x": -1, "_y": 1}, {"_time": 28.211, "_x": 1, "_y": 0}, {"_time": 28.339, "_x": -1, "_y": -1}, {"_time": 28.471, "_x": 0, "_y": 0}, {"_time": 28.864, "_x": -1, "_y": -1}, {"_time": 29.037, "_x": -1, "_y": 0}, {"_time": 29.168, "_x": -1, "_y": 1}, {"_time": 29.651, "_x": 1, "_y": 1}, {"_time": 29.738, "_x": 1, "_y": -1}, {"_time": 29.826, "_x": -1, "_y": -1}, {"_time": 29.913, "_x": -1, "_y": 1}, {"_time": 30, "_x": 1, "_y": 1}, {"_time": 30.087, "_x": 1, "_y": -1}, {"_time": 30.175, "_x": -1, "_y": -1}, {"_time": 30.262, "_x": -1, "_y": 1}, {"_time": 30.349, "_x": 1, "_y": 1}, {"_time": 30.436, "_x": 1, "_y": -1}, {"_time": 30.524, "_x": -1, "_y": -1}, {"_time": 30.611, "_x": -1, "_y": 1}, {"_time": 30.697, "_x": 1, "_y": 1}, {"_time": 30.785, "_x": 1, "_y": 1}, {"_time": 30.872, "_x": 1, "_y": 1}, {"_time": 31.002, "_x": -1, "_y": 0}, {"_time": 31.13, "_x": 1, "_y": -1}, {"_time": 31.262, "_x": 0, "_y": 0}, {"_time": 31.656, "_x": -1, "_y": 1}, {"_time": 31.829, "_x": -1, "_y": 0}, {"_time": 31.96, "_x": -1, "_y": -1}, {"_time": 32.135, "_x": -1, "_y": -1}, {"_time": 32.353, "_x": 1, "_y": 0}, {"_time": 32.658, "_x": -1, "_y": 0}, {"_time": 32.921, "_x": 1, "_y": -1}, {"_time": 33.356, "_x": 0, "_y": 1}, {"_time": 33.399, "_x": 0, "_y": 0}, {"_time": 33.444, "_x": 0, "_y": -1}, {"_time": 33.748, "_x": -1, "_y": 1}, {"_time": 34.838, "_x": -1, "_y": -1}, {"_time": 34.969, "_x": 0, "_y": -1}, {"_time": 35.186, "_x": 1, "_y": -1}, {"_time": 35.929, "_x": -1, "_y": 0}, {"_time": 36.581, "_x": 1, "_y": 0}, {"_time": 36.931, "_x": -1, "_y": 1}, {"_time": 37.062, "_x": -1, "_y": 0}, {"_time": 37.28, "_x": -1, "_y": -1}, {"_time": 37.629, "_x": -1, "_y": 1}, {"_time": 37.76, "_x": -1, "_y": 0}, {"_time": 37.978, "_x": -1, "_y": -1}, {"_time": 38.327, "_x": 1, "_y": 1}, {"_time": 38.458, "_x": 0, "_y": -1}, {"_time": 38.632, "_x": 0, "_y": 1}, {"_time": 38.937, "_x": 1, "_y": -1}, {"_time": 39.198, "_x": -1, "_y": 1}, {"_time": 39.33, "_x": -1, "_y": -1}, {"_time": 39.417, "_x": 0, "_y": -1}, {"_time": 39.504, "_x": 1, "_y": -1}, {"_time": 39.591, "_x": 1, "_y": 0}, {"_time": 39.679, "_x": 0, "_y": 0}, {"_time": 39.766, "_x": -1, "_y": 0}, {"_time": 39.853, "_x": -1, "_y": 1}, {"_time": 39.94, "_x": 0, "_y": 1}, {"_time": 40.027, "_x": 1, "_y": 1}, {"_time": 40.767, "_x": 1, "_y": -1}, {"_time": 41.466, "_x": -1, "_y": -1}, {"_time": 42.077, "_x": 1, "_y": 1}, {"_time": 42.382, "_x": -1, "_y": 1}, {"_time": 42.644, "_x": 1, "_y": 0}, {"_time": 42.818, "_x": -1, "_y": 0}, {"_time": 43.559, "_x": -1, "_y": -1}, {"_time": 44.257, "_x": 1, "_y": -1}, {"_time": 44.91, "_x": -1, "_y": 1}, {"_time": 46.305, "_x": -1, "_y": 1}, {"_time": 47.701, "_x": -1, "_y": 1}, {"_time": 49.095, "_x": -1, "_y": 1}, {"_time": 50.449, "_x": -1, "_y": 1}, {"_time": 50.536, "_x": -1, "_y": 0}, {"_time": 50.667, "_x": 0, "_y": -1}, {"_time": 50.841, "_x": 1, "_y": 1}, {"_time": 51.016, "_x": -1, "_y": 0}, {"_time": 51.234, "_x": 1, "_y": -1}, {"_time": 51.321, "_x": 1, "_y": 0}, {"_time": 51.494, "_x": 0, "_y": 1}, {"_time": 51.67, "_x": -1, "_y": -1}, {"_time": 51.843, "_x": 1, "_y": 0}, {"_time": 52.062, "_x": -1, "_y": 0}, {"_time": 52.236, "_x": 1, "_y": 1}, {"_time": 52.411, "_x": -1, "_y": 1}, {"_time": 52.585, "_x": 1, "_y": 0}, {"_time": 52.761, "_x": -1, "_y": -1}, {"_time": 52.848, "_x": 0, "_y": 0}, {"_time": 52.933, "_x": 1, "_y": 1}, {"_time": 53.109, "_x": 0, "_y": -1}, {"_time": 53.283, "_x": -1, "_y": 1}, {"_time": 53.546, "_x": 1, "_y": -1}, {"_time": 53.676, "_x": -1, "_y": 0}, {"_time": 53.895, "_x": 1, "_y": 0}, {"_time": 54.2, "_x": -1, "_y": -1}, {"_time": 56.205, "_x": -1, "_y": 1}, {"_time": 56.336, "_x": 0, "_y": -1}, {"_time": 56.465, "_x": 0, "_y": 1}, {"_time": 56.55, "_x": -1, "_y": 0}, {"_time": 56.727, "_x": 1, "_y": 1}, {"_time": 56.901, "_x": 0, "_y": -1}, {"_time": 57.076, "_x": 0, "_y": 1}, {"_time": 57.161, "_x": 1, "_y": 0}, {"_time": 57.337, "_x": -1, "_y": 1}, {"_time": 57.512, "_x": -1, "_y": -1}, {"_time": 57.686, "_x": 1, "_y": 1}, {"_time": 57.861, "_x": -1, "_y": 0}, {"_time": 57.948, "_x": 0, "_y": -1}, {"_time": 58.121, "_x": 0, "_y": 0}, {"_time": 58.297, "_x": 1, "_y": -1}, {"_time": 58.471, "_x": -1, "_y": 1}, {"_time": 58.558, "_x": 0, "_y": 0}, {"_time": 58.733, "_x": -1, "_y": -1}, {"_time": 58.864, "_x": 1, "_y": 1}, {"_time": 58.907, "_x": 1, "_y": 0}, {"_time": 58.95, "_x": 1, "_y": -1}, {"_time": 59.212, "_x": -1, "_y": 1}, {"_time": 59.255, "_x": -1, "_y": 0}, {"_time": 59.298, "_x": -1, "_y": -1}, {"_time": 59.562, "_x": 1, "_y": 1}, {"_time": 59.605, "_x": 1, "_y": 0}, {"_time": 59.648, "_x": 1, "_y": -1}, {"_time": 59.911, "_x": -1, "_y": 1}, {"_time": 59.954, "_x": -1, "_y": 0}, {"_time": 59.997, "_x": -1, "_y": -1}, {"_time": 60.348, "_x": -1, "_y": 1}, {"_time": 60.435, "_x": -1, "_y": -1}, {"_time": 60.523, "_x": 1, "_y": -1}, {"_time": 60.61, "_x": 1, "_y": 1}, {"_time": 60.697, "_x": -1, "_y": 1}, {"_time": 60.784, "_x": -1, "_y": -1}, {"_time": 60.872, "_x": -1, "_y": 1}, {"_time": 60.958, "_x": 1, "_y": 1}, {"_time": 61.045, "_x": 1, "_y": -1}, {"_time": 61.132, "_x": -1, "_y": -1}, {"_time": 61.219, "_x": -1, "_y": 1}, {"_time": 61.307, "_x": 1, "_y": 1}, {"_time": 61.394, "_x": 1, "_y": -1}, {"_time": 61.482, "_x": -1, "_y": -1}, {"_time": 61.698, "_x": -1, "_y": 1}, {"_time": 61.873, "_x": 0, "_y": -1}, {"_time": 62.047, "_x": 0, "_y": 1}, {"_time": 62.132, "_x": -1, "_y": 0}, {"_time": 62.309, "_x": 1, "_y": 1}, {"_time": 62.483, "_x": 0, "_y": -1}, {"_time": 62.658, "_x": 0, "_y": 1}, {"_time": 62.743, "_x": 1, "_y": 0}, {"_time": 62.919, "_x": -1, "_y": 1}, {"_time": 63.094, "_x": -1, "_y": -1}, {"_time": 63.268, "_x": 1, "_y": 1}, {"_time": 63.443, "_x": -1, "_y": 0}, {"_time": 63.53, "_x": 0, "_y": -1}, {"_time": 63.703, "_x": 0, "_y": 0}, {"_time": 63.879, "_x": 1, "_y": -1}, {"_time": 64.053, "_x": -1, "_y": 1}, {"_time": 64.14, "_x": 0, "_y": 0}, {"_time": 64.315, "_x": -1, "_y": -1}, {"_time": 64.49, "_x": 1, "_y": -1}, {"_time": 64.533, "_x": 1, "_y": 0}, {"_time": 64.576, "_x": 1, "_y": 1}, {"_time": 64.838, "_x": -1, "_y": -1}, {"_time": 64.881, "_x": -1, "_y": 0}, {"_time": 64.925, "_x": -1, "_y": 1}, {"_time": 65.144, "_x": 1, "_y": -1}, {"_time": 65.186, "_x": 1, "_y": 0}, {"_time": 65.231, "_x": 1, "_y": 1}, {"_time": 65.492, "_x": -1, "_y": -1}, {"_time": 65.535, "_x": -1, "_y": 0}, {"_time": 65.578, "_x": -1, "_y": 1}, {"_time": 65.929, "_x": 1, "_y": 1}, {"_time": 66.016, "_x": 1, "_y": -1}, {"_time": 66.104, "_x": -1, "_y": -1}, {"_time": 66.191, "_x": -1, "_y": 1}, {"_time": 66.278, "_x": 1, "_y": 1}, {"_time": 66.365, "_x": 1, "_y": -1}, {"_time": 66.453, "_x": 1, "_y": 1}, {"_time": 66.539, "_x": -1, "_y": 1}, {"_time": 66.626, "_x": -1, "_y": -1}, {"_time": 66.713, "_x": 1, "_y": -1}, {"_time": 66.8, "_x": 1, "_y": 1}, {"_time": 66.888, "_x": -1, "_y": 1}, {"_time": 66.975, "_x": -1, "_y": -1}, {"_time": 67.063, "_x": 1, "_y": -1}, {"_time": 67.151, "_x": 1, "_y": 1}, {"_time": 67.236, "_x": 0, "_y": 1}, {"_time": 67.323, "_x": -1, "_y": 1}, {"_time": 67.41, "_x": -1, "_y": 0}, {"_time": 67.499, "_x": 0, "_y": 0}, {"_time": 67.586, "_x": 1, "_y": 0}, {"_time": 67.674, "_x": 1, "_y": -1}, {"_time": 67.761, "_x": 0, "_y": -1}, {"_time": 67.848, "_x": -1, "_y": -1}, {"_time": 67.935, "_x": -1, "_y": 0}, {"_time": 68.022, "_x": -1, "_y": 1}, {"_time": 68.109, "_x": 0, "_y": 1}, {"_time": 68.196, "_x": 0, "_y": 0}, {"_time": 68.283, "_x": 0, "_y": -1}, {"_time": 68.372, "_x": 1, "_y": -1}, {"_time": 68.457, "_x": 1, "_y": 0}, {"_time": 68.544, "_x": 1, "_y": 1}, {"_time": 68.633, "_x": 0, "_y": 1}, {"_time": 68.72, "_x": -1, "_y": 1}, {"_time": 68.807, "_x": -1, "_y": 0}, {"_time": 68.894, "_x": 0, "_y": 0}, {"_time": 68.981, "_x": 1, "_y": 0}, {"_time": 69.069, "_x": 1, "_y": -1}, {"_time": 69.156, "_x": 0, "_y": -1}, {"_time": 69.243, "_x": -1, "_y": -1}, {"_time": 69.33, "_x": -1, "_y": 0}, {"_time": 69.417, "_x": -1, "_y": 1}, {"_time": 69.504, "_x": 0, "_y": 1}, {"_time": 69.591, "_x": 0, "_y": 0}, {"_time": 69.678, "_x": 0, "_y": -1}, {"_time": 69.767, "_x": 1, "_y": -1}, {"_time": 69.854, "_x": 1, "_y": 0}, {"_time": 69.941, "_x": 0, "_y": 0}, {"_time": 70.028, "_x": -1, "_y": 0}, {"_time": 70.115, "_x": -1, "_y": 1}, {"_time": 70.202, "_x": 0, "_y": 1}, {"_time": 70.289, "_x": 1, "_y": 1}, {"_time": 70.376, "_x": 1, "_y": 0}, {"_time": 70.465, "_x": 1, "_y": -1}, {"_time": 70.549, "_x": 0, "_y": -1}, {"_time": 70.638, "_x": 0, "_y": 0}, {"_time": 70.725, "_x": 0, "_y": 1}, {"_time": 70.812, "_x": -1, "_y": 1}, {"_time": 70.899, "_x": -1, "_y": 0}, {"_time": 70.986, "_x": 0, "_y": 0}, {"_time": 71.073, "_x": 1, "_y": 0}, {"_time": 71.162, "_x": 1, "_y": -1}, {"_time": 71.249, "_x": 0, "_y": -1}, {"_time": 71.336, "_x": -1, "_y": -1}, {"_time": 71.423, "_x": -1, "_y": 0}, {"_time": 71.51, "_x": 0, "_y": 0}, {"_time": 71.597, "_x": 1, "_y": 0}, {"_time": 71.684, "_x": 1, "_y": 1}, {"_time": 71.771, "_x": 0, "_y": 1}, {"_time": 71.86, "_x": 0, "_y": 0}, {"_time": 71.947, "_x": 0, "_y": -1}, {"_time": 72.034, "_x": -1, "_y": -1}, {"_time": 72.121, "_x": -1, "_y": 0}, {"_time": 72.208, "_x": -1, "_y": 1}, {"_time": 72.295, "_x": 0, "_y": 1}, {"_time": 72.382, "_x": 1, "_y": 1}, {"_time": 72.469, "_x": 1, "_y": 0}, {"_time": 72.558, "_x": 1, "_y": -1}, {"_time": 72.645, "_x": 1, "_y": -1}, {"_time": 72.732, "_x": 1, "_y": -1}, {"_time": 72.906, "_x": 0, "_y": 1}, {"_time": 73.079, "_x": -1, "_y": -1}, {"_time": 73.255, "_x": 1, "_y": 0}, {"_time": 73.43, "_x": -1, "_y": 1}, {"_time": 73.604, "_x": -1, "_y": -1}, {"_time": 73.779, "_x": 0, "_y": 1}, {"_time": 73.953, "_x": 0, "_y": -1}, {"_time": 74.127, "_x": 1, "_y": 1}, {"_time": 74.302, "_x": -1, "_y": 0}, {"_time": 74.476, "_x": 1, "_y": -1}, {"_time": 74.651, "_x": 0, "_y": 1}, {"_time": 74.825, "_x": -1, "_y": -1}, {"_time": 75, "_x": 1, "_y": -1}, {"_time": 75.174, "_x": -1, "_y": 0}, {"_time": 75.348, "_x": 1, "_y": 0}, {"_time": 75.523, "_x": -1, "_y": 1}, {"_time": 75.697, "_x": 0, "_y": -1}, {"_time": 75.872, "_x": 1, "_y": 1}, {"_time": 76.046, "_x": -1, "_y": 0}, {"_time": 76.22, "_x": 1, "_y": -1}, {"_time": 76.395, "_x": 1, "_y": 1}, {"_time": 76.569, "_x": 0, "_y": -1}, {"_time": 76.744, "_x": 0, "_y": 1}, {"_time": 76.918, "_x": -1, "_y": -1}, {"_time": 77.093, "_x": 1, "_y": 0}, {"_time": 77.267, "_x": -1, "_y": 1}, {"_time": 77.441, "_x": 0, "_y": -1}, {"_time": 77.616, "_x": 1, "_y": 1}, {"_time": 77.79, "_x": -1, "_y": 0}, {"_time": 77.965, "_x": 1, "_y": -1}, {"_time": 78.05, "_x": 1, "_y": 0}, {"_time": 78.139, "_x": 1, "_y": 1}, {"_time": 78.226, "_x": 0, "_y": 1}, {"_time": 78.313, "_x": 0, "_y": 0}, {"_time": 78.4, "_x": 0, "_y": -1}, {"_time": 78.487, "_x": -1, "_y": -1}]}